INSTALL
LICENSE
MANIFEST.in
README
setup.py
bin/cssmergemedia
cssmergemedia.egg-info/PKG-INFO
cssmergemedia.egg-info/SOURCES.txt
cssmergemedia.egg-info/dependency_links.txt
cssmergemedia.egg-info/requires.txt
cssmergemedia.egg-info/top_level.txt
cssmergemedialib/__init__.py
cssmergemedialib/meta.py
test/testcssmergemedialib.py