Metadata-Version: 1.0
Name: cssmergemedia
Version: 0.1.1
Summary: CSS Merge Media merges identical media queries in your CSS
Home-page: UNKNOWN
Author: Adrien Kohlbecker
Author-email: UNKNOWN
License: UNKNOWN
Platform: UNKNOWN
